MoyNalogPy/CustomRequests.py
MoyNalogPy/MoyNalog.py
MoyNalogPy/__init__.py
MoyNalogPy/auth.py
MoyNalogPy/token_refresh.py
MoyNalogPy/schemas/__init__.py
MoyNalogPy/schemas/schemas.py
moy_nalog_py-0.2.1.dist-info/METADATA
moy_nalog_py-0.2.1.dist-info/WHEEL
moy_nalog_py-0.2.1.dist-info/top_level.txt
moy_nalog_py-0.2.1.dist-info/RECORD
