Metadata-Version: 2.4
Name: moy-nalog-py
Version: 0.2.1
Summary: Python клиент для работы с API сервиса Мой налог
Home-page: https://github.com/senylar/MoyNalogPy
Author: senylar
Author-email: senylar <senyvlar@gmail.com>
Project-URL: Homepage, https://github.com/senylar/MoyNalogPy
Classifier: Programming Language :: Python :: 3
Classifier: License :: OSI Approved :: MIT License
Classifier: Operating System :: OS Independent
Requires-Python: >=3.6
Requires-Dist: pydantic>=2.10.6
Requires-Dist: requests>=2.32.3
Requires-Dist: sqlmodel>=0.0.24
Dynamic: author
Dynamic: home-page
Dynamic: requires-python
